torchcrepeV2/__init__.py
torchcrepeV2/convert_h5_to_pt.py
torchcrepeV2/core.py
torchcrepeV2/crepe_model.py
torchcrepeV2/model-full-crepe.pt
torchcrepeV2/test_example.py
torchcrepeV2/utils.py
torchcrepeV2-0.1.3.dist-info/LICENSE
torchcrepeV2-0.1.3.dist-info/METADATA
torchcrepeV2-0.1.3.dist-info/WHEEL
torchcrepeV2-0.1.3.dist-info/top_level.txt
torchcrepeV2-0.1.3.dist-info/RECORD
