Metadata-Version: 2.1
Name: torchcrepeV2
Version: 0.1.3
Summary: Crepe pitch detection in PyTorch
Home-page: https://github.com/gudgud96/torchcrepeV2
Author: Hao Hao Tan
Author-email: Hao Hao Tan <helloharry66@gmail.com>
Project-URL: Homepage, https://github.com/gudgud96/torchcrepeV2
Classifier: Programming Language :: Python :: 3
Classifier: License :: OSI Approved :: MIT License
Classifier: Operating System :: OS Independent
Requires-Python: >=3.7
License-File: LICENSE
Requires-Dist: tensorflow
Requires-Dist: torch
Requires-Dist: numpy
Requires-Dist: crepe (==0.0.12)
Requires-Dist: librosa (==0.9.1)
Requires-Dist: hmmlearn (==0.2.7)
